bumble_bencoding/__init__.py
bumble_bencoding/codec/__init__.py
bumble_bencoding/codec/decoder.py
bumble_bencoding/codec/encoder.py
bumble_bencoding/codec/exceptions.py
bumble_bencoding/codec/optimize.py
bumble_bencoding/utils/abstract_codec.py
bumble_bencoding/utils/pipeline.py
bumble_bencoding/utils/secure_codecs.py
bumble_bencoding/utils/standard_codecs.py
bumble_bencoding-0.0.3.dist-info/LICENSE
bumble_bencoding-0.0.3.dist-info/WHEEL
bumble_bencoding-0.0.3.dist-info/METADATA
bumble_bencoding-0.0.3.dist-info/RECORD
