Metadata-Version: 2.1
Name: bumble_bencoding
Version: 0.0.3
Summary: .. include:: ../README.md
Author: Alyce Osbourne
Classifier: License :: OSI Approved :: GNU General Public License v3 or later (GPLv3+)
